hepdata/__init__.py
hepdata/client.py
hepdata/exceptions.py
hepdata-0.2.1.dist-info/DESCRIPTION.rst
hepdata-0.2.1.dist-info/METADATA
hepdata-0.2.1.dist-info/RECORD
hepdata-0.2.1.dist-info/WHEEL
hepdata-0.2.1.dist-info/metadata.json
hepdata-0.2.1.dist-info/top_level.txt
