Metadata-Version: 2.0
Name: hepdata
Version: 0.2.1
Summary: HEPdata
Home-page: https://github.com/wellfire/hepdata-matchinggifts
Author: Ben Lopatin
Author-email: ben@wellfire.co
License: BSD
Keywords: hepdata
Platform: UNKNOWN
Classifier: Development Status :: 2 - Pre-Alpha
Classifier: Intended Audience :: Developers
Classifier: License :: OSI Approved :: BSD License
Classifier: Natural Language :: English
Classifier: Programming Language :: Python :: 2
Classifier: Programming Language :: Python :: 2.7
Classifier: Programming Language :: Python :: 3
Classifier: Programming Language :: Python :: 3.3
Classifier: Programming Language :: Python :: 3.4
Classifier: Programming Language :: Python :: 3.5
Requires-Dist: requests (<3.0,>=2.0)
Requires-Dist: xmltodict (<1.0,>=0.10.0)
